main/__init__.py
main/main.py
project/__init__.py
project/config_utils.py
project/logger.py
project/config/__init__.py
project/config/env.py
project/model/__init__.py
project/model/project.py
siddhivinayak.sk.project1-0.0.0.dist-info/LICENSE
siddhivinayak.sk.project1-0.0.0.dist-info/METADATA
siddhivinayak.sk.project1-0.0.0.dist-info/WHEEL
siddhivinayak.sk.project1-0.0.0.dist-info/entry_points.txt
siddhivinayak.sk.project1-0.0.0.dist-info/top_level.txt
siddhivinayak.sk.project1-0.0.0.dist-info/RECORD
