Metadata-Version: 2.1
Name: siddhivinayak.sk.project1
Version: 0.0.0
Summary: Test Project1
Home-page: https://www.siddhivinayaksk.co.in/
Author: Sandeep Kumar
Author-email: test@test.com
License: MIT
Classifier: Development Status :: 2 - Pre-Alpha
Classifier: License :: OSI Approved :: MIT License
Classifier: Programming Language :: Python
Classifier: Programming Language :: Python :: 2
Classifier: Programming Language :: Python :: 2.7
Classifier: Programming Language :: Python :: 3
Classifier: Programming Language :: Python :: 3.4
Classifier: Programming Language :: Python :: 3.5
Classifier: Programming Language :: Python :: 3.6
Classifier: Programming Language :: Python :: 3.7
License-File: LICENSE
Requires-Dist: PyYAML (==6.0)
Requires-Dist: python-gitlab (==3.7.0)
Requires-Dist: tomark (==0.1.4)
Requires-Dist: fs (==2.4.16)
Requires-Dist: colorama (==0.4.5)
Requires-Dist: xmlformatter (==0.2.4)
Requires-Dist: ruamel.yaml (==0.17.21)
Requires-Dist: python-dotenv (==0.21.0)
Requires-Dist: pytest (==7.2.0)
Requires-Dist: coverage (>=5.5)
Requires-Dist: pytest-cov (>=2.11.1)
